cryptocoin
