Metadata-Version: 1.1
Name: cryptocoin
Version: 0.0.0.dev2
Summary: Cryptocurrencies for Humans
Home-page: http://github.com/lyndsysimon/cryptocoin
Author: UNKNOWN
Author-email: UNKNOWN
License: Apache
Keywords: bitcoin cryptocurrency
Platform: UNKNOWN
Classifier: Development Status :: 2 - Pre-Alpha
Classifier: Programming Language :: Python :: 2.7
Classifier: Programming Language :: Python :: 3.3
Classifier: Programming Language :: Python :: 3.4
Classifier: License :: OSI Approved :: Apache Software License
